AUTHORS
LICENSE.txt
MANIFEST.in
README.md
setup.cfg
setup.py
django_wtfd/__init__.py
django_wtfd/models.py
django_wtfd/tests.py
django_wtfd.egg-info/PKG-INFO
django_wtfd.egg-info/SOURCES.txt
django_wtfd.egg-info/dependency_links.txt
django_wtfd.egg-info/not-zip-safe
django_wtfd.egg-info/top_level.txt
django_wtfd/management/__init__.py
django_wtfd/management/commands/__init__.py
django_wtfd/management/commands/wtfd.py