Metadata-Version: 1.1
Name: django-wtfd
Version: 0.1.4
Summary: Forcing developers to write docstrings.
Home-page: https://github.com/postatum/django-wtfd
Author: Artem Kostiuk
Author-email: postatum@gmail.com
License: UNKNOWN
Download-URL: https://github.com/postatum/django-wtfd/tarball/0.1.4
Keywords: docs,docstrings
Platform: UNKNOWN
